[{"COUNTRYID": 108, "ISO2CODE": "BI", "COUNTRYNAME": "Burundi", "STATUSDATE": "01.01.2008", "STATUSRANK": 3, "STATUSID": 7, "STATUSDESC": "In force"}, {"COUNTRYID": 404, "ISO2CODE": "KE", "COUNTRYNAME": "Kenya", "STATUSDATE": "01.01.2008", "STATUSRANK": 3, "STATUSID": 7, "STATUSDESC": "In force"}, {"COUNTRYID": 646, "ISO2CODE": "RW", "COUNTRYNAME": "Rwanda", "STATUSDATE": "01.01.2008", "STATUSRANK": 3, "STATUSID": 7, "STATUSDESC": "In force"}, {"COUNTRYID": 800, "ISO2CODE": "UG", "COUNTRYNAME": "Uganda", "STATUSDATE": "01.01.2008", "STATUSRANK": 3, "STATUSID": 7, "STATUSDESC": "In force"}, {"COUNTRYID": 834, "ISO2CODE": "TZ", "COUNTRYNAME": "Tanzania, United Republic of", "STATUSDATE": "01.01.2008", "STATUSRANK": 3, "STATUSID": 7, "STATUSDESC": "In force"}, {"COUNTRYID": 918, "ISO2CODE": "EU", "COUNTRYNAME": "European Union", "STATUSDATE": "01.01.2008", "STATUSRANK": 3, "STATUSID": 7, "STATUSDESC": "In force"}]