[{"COUNTRYID": 174, "ISO2CODE": "KM", "COUNTRYNAME": "Comoros", "STATUSDATE": "07.02.2019", "STATUSRANK": 2, "STATUSID": 7, "STATUSDESC": "In force"}, {"COUNTRYID": 231, "ISO2CODE": "ET", "COUNTRYNAME": "Ethiopia", "STATUSDATE": "07.02.2004", "STATUSRANK": 1, "STATUSID": 2, "STATUSDESC": "Negotiations launched"}, {"COUNTRYID": 232, "ISO2CODE": "ER", "COUNTRYNAME": "Eritrea", "STATUSDATE": "07.02.2004", "STATUSRANK": 1, "STATUSID": 2, "STATUSDESC": "Negotiations launched"}, {"COUNTRYID": 262, "ISO2CODE": "DJ", "COUNTRYNAME": "Djibouti", "STATUSDATE": "07.02.2004", "STATUSRANK": 1, "STATUSID": 2, "STATUSDESC": "Negotiations launched"}, {"COUNTRYID": 450, "ISO2CODE": "MG", "COUNTRYNAME": "Madagascar", "STATUSDATE": "14.05.2012", "STATUSRANK": 3, "STATUSID": 7, "STATUSDESC": "In force"}, {"COUNTRYID": 454, "ISO2CODE": "MW", "COUNTRYNAME": "Malawi", "STATUSDATE": "07.02.2004", "STATUSRANK": 1, "STATUSID": 2, "STATUSDESC": "Negotiations launched"}, {"COUNTRYID": 480, "ISO2CODE": "MU", "COUNTRYNAME": "Mauritius", "STATUSDATE": "14.05.2012", "STATUSRANK": 3, "STATUSID": 7, "STATUSDESC": "In force"}, {"COUNTRYID": 690, "ISO2CODE": "SC", "COUNTRYNAME": "Seychelles", "STATUSDATE": "14.05.2012", "STATUSRANK": 3, "STATUSID": 7, "STATUSDESC": "In force"}, {"COUNTRYID": 716, "ISO2CODE": "ZW", "COUNTRYNAME": "Zimbabwe", "STATUSDATE": "14.05.2012", "STATUSRANK": 3, "STATUSID": 7, "STATUSDESC": "In force"}, {"COUNTRYID": 736, "ISO2CODE": "SD", "COUNTRYNAME": "Sudan", "STATUSDATE": "07.02.2004", "STATUSRANK": 1, "STATUSID": 2, "STATUSDESC": "Negotiations launched"}, {"COUNTRYID": 894, "ISO2CODE": "ZM", "COUNTRYNAME": "Zambia", "STATUSDATE": "07.02.2004", "STATUSRANK": 1, "STATUSID": 2, "STATUSDESC": "Negotiations launched"}, {"COUNTRYID": 918, "ISO2CODE": "EU", "COUNTRYNAME": "European Union", "STATUSDATE": "14.05.2012", "STATUSRANK": 3, "STATUSID": 7, "STATUSDESC": "In force"}]